{
    "key": "voting_engagement",
    "name": "Voting Engagement",
    "kind": "standalone",
    "category": "Engagement",
    "summary": "Scores each user by how widely their wallets' voting history uses the full rating scale.",
    "description": "### What it does\nScores how varied each user's linked voting history is.\n\n### How it works\n- Users and their wallets come from DeepID; each wallet is resolved to its `collection_id`(s) through the wallet collections CSV.\n- Votes are read from the votes CSV, grouped by `collection_id`.\n- Using many different ratings increases the score.\n- Repeating the same rating lowers the score.\n- Scores are shown on a 0 to 1 scale.\n\n### Input\nUpload two CSV files: the votes CSV and the wallet collections CSV (mapping each voting `collection_id` to a wallet `address`).\n\n### Output\n- CSV file with `did` and `voting_engagement`.\n- JSON file with vote distribution details for each scored user.",
    "version": "1.0.0",
    "inputs": [
        {
            "key": "votes",
            "label": "Vote History (CSV)",
            "description": "Upload a CSV file of votes. Each row needs `collection_id`, `question_id`, and an `answer` from `skip` or `1` to `10`.",
            "type": "csv",
            "csv": {
                "hasHeader": true,
                "delimiter": ",",
                "maxRows": 200000,
                "maxBytes": 104857600,
                "columns": [
                    {
                        "key": "id",
                        "type": "number",
                        "required": false,
                        "description": "Optional source row ID."
                    },
                    {
                        "key": "event_id",
                        "type": "number",
                        "required": false,
                        "description": "Optional vote event ID."
                    },
                    {
                        "key": "answer",
                        "type": "enum",
                        "enum": [
                            "skip",
                            "1",
                            "2",
                            "3",
                            "4",
                            "5",
                            "6",
                            "7",
                            "8",
                            "9",
                            "10"
                        ],
                        "description": "Vote answer: `skip` or a number from `1` to `10`."
                    },
                    {
                        "key": "created_on",
                        "type": "date",
                        "required": false,
                        "description": "Optional time when the vote was created."
                    },
                    {
                        "key": "updated_on",
                        "type": "date",
                        "required": false,
                        "description": "Optional time when the vote was last updated."
                    },
                    {
                        "key": "question_id",
                        "type": "string",
                        "description": "ID of the question or proposal."
                    },
                    {
                        "key": "balance",
                        "type": "number",
                        "required": false,
                        "description": "Optional balance saved with the vote."
                    },
                    {
                        "key": "stake",
                        "type": "number",
                        "required": false,
                        "description": "Optional stake saved with the vote."
                    },
                    {
                        "key": "collection_id",
                        "type": "string",
                        "description": "Voting identity used to group votes before mapping them to SubIDs."
                    },
                    {
                        "key": "vote_id",
                        "type": "number",
                        "required": false,
                        "description": "Optional unique vote ID."
                    }
                ]
            }
        },
        {
            "key": "wallet_collections",
            "label": "Wallet Collections (CSV)",
            "description": "CSV mapping each voting `collection_id` to a wallet `address`. Each user's wallets are resolved to their collection_id(s) and joined to the votes CSV.",
            "type": "csv",
            "csv": {
                "hasHeader": true,
                "delimiter": ",",
                "maxRows": 200000,
                "maxBytes": 104857600,
                "columns": [
                    {
                        "key": "collection_id",
                        "type": "string",
                        "description": "Voting identity that groups votes in the votes CSV."
                    },
                    {
                        "key": "address",
                        "type": "string",
                        "description": "Wallet address linked to the collection_id; matched against user wallets (case-insensitive)."
                    },
                    {
                        "key": "network",
                        "type": "string",
                        "required": false,
                        "description": "Chain the wallet belongs to (e.g. Ethereum, Cardano). Not used for matching."
                    }
                ]
            }
        }
    ],
    "outputs": [
        {
            "key": "voting_engagement",
            "label": "Voting Engagement (CSV)",
            "description": "CSV file with one row per SubID and the final voting engagement score.",
            "type": "csv",
            "csv": {
                "hasHeader": true,
                "delimiter": ",",
                "columns": [
                    {
                        "key": "did",
                        "type": "string",
                        "description": "SubID from the uploaded JSON input."
                    },
                    {
                        "key": "voting_engagement",
                        "type": "number",
                        "description": "Final voting engagement score from 0 to 1."
                    }
                ]
            }
        },
        {
            "key": "voting_engagement_details",
            "label": "Voting Engagement Details (JSON)",
            "description": "JSON file with vote distribution details for each scored SubID.",
            "type": "json"
        }
    ],
    "dependencies": [{ "key": "deep-id" }],
    "runtime": "typescript"
}
